pgtricks/__init__.py
pgtricks/mergesort.py
pgtricks/pg_dump_splitsort.py
pgtricks/pg_incremental_backup.py
pgtricks/pg_split_schema_dump.py
pgtricks/version.py
pgtricks-1.1.0.dist-info/LICENSE
pgtricks-1.1.0.dist-info/METADATA
pgtricks-1.1.0.dist-info/WHEEL
pgtricks-1.1.0.dist-info/entry_points.txt
pgtricks-1.1.0.dist-info/top_level.txt
pgtricks-1.1.0.dist-info/RECORD
