Metadata-Version: 2.1
Name: pgtricks
Version: 1.1.0
Summary: PostgreSQL utilities
Home-page: https://github.com/akaihola/pgtricks
Author: Antti Kaihola
Author-email: 13725+akaihola@users.noreply.github.com
License: BSD
Project-URL: Source Code, https://github.com/akaihola/pgtricks
Project-URL: Change Log, https://github.com/akaihola/pgtricks/CHANGES.rst
Keywords: database,postgresql,backup,git
Classifier: Development Status :: 4 - Beta
Classifier: Environment :: Console
Classifier: Intended Audience :: System Administrators
Classifier: License :: OSI Approved :: BSD License
Classifier: Operating System :: OS Independent
Classifier: Programming Language :: Python :: 3.7
Classifier: Programming Language :: Python :: 3.8
Classifier: Programming Language :: Python :: 3.9
Classifier: Programming Language :: Python :: 3.10
Classifier: Programming Language :: Python :: 3.11
Classifier: Programming Language :: Python :: 3.12
Classifier: Topic :: Database
Classifier: Topic :: System :: Archiving :: Backup
Requires-Python: >=3.7
License-File: LICENSE
Provides-Extra: release
Requires-Dist: darkgray-dev-tools ~=0.0.2 ; extra == 'release'
Provides-Extra: test
Requires-Dist: darker[isort] ; extra == 'test'
Requires-Dist: flake8 ; extra == 'test'
Requires-Dist: mypy ; extra == 'test'
Requires-Dist: pylint ; extra == 'test'
Requires-Dist: pytest ; extra == 'test'
Requires-Dist: pytest-mypy ; extra == 'test'
